getregdf/README.md
getregdf/__init__.py
getregdf/requirements.txt
getregdf/thirdparty.json
getregdf-0.10.dist-info/LICENSE.rst
getregdf-0.10.dist-info/METADATA
getregdf-0.10.dist-info/WHEEL
getregdf-0.10.dist-info/top_level.txt
getregdf-0.10.dist-info/RECORD
