Metadata-Version: 2.1
Name: getregdf
Version: 0.10
Summary: reg.exe query to pandas DataFrame
Home-page: https://github.com/hansalemaos/getregdf
Author: Johannes Fischer
Author-email: aulasparticularesdealemaosp@gmail.com
License: MIT
Keywords: reg.exe,regedit,pandas
Classifier: Development Status :: 4 - Beta
Classifier: Programming Language :: Python :: 3 :: Only
Classifier: Programming Language :: Python :: 3.10
Classifier: Topic :: Software Development :: Libraries :: Python Modules
Classifier: Topic :: Utilities
License-File: LICENSE.rst
Requires-Dist: a-pandas-ex-df-to-string
Requires-Dist: a-pandas-ex-fastloc
Requires-Dist: flatten-everything
Requires-Dist: multisubprocess
Requires-Dist: pandas
